{
  "version": "1.0",
  "bookId": "10028",
  "volumeNumber": 1,
  "pageNumber": 415,
  "encoding": "utf-8",
  "source": "lib.eshia.ir",
  "html": "\n\n<p class=\"rfdToc2\">الفصل (٢٣) موجبات\r\nالوضوء ونواقضه ......................................................  ١٤١</p>\n<p class=\"rfdToc2\">الفصل (٢٤) غايات\r\nالوضوء ..................................................................  ١٤٣</p>\n<p class=\"rfdToc2\">الفصل (٢٥) الوضوءات\r\nالمستحبة .............................................................  ١٤٨</p>\n<p class=\"rfdToc2\">الفصل (٢٦) مستحبات\r\nالوضوء ..............................................................  ١٥٣</p>\n<p class=\"rfdToc2\">الفصل (٢٧) مكروهات\r\nالوضوء ..............................................................  ١٥٥</p>\n<p class=\"rfdToc2\">الفصل (٢٨) أفعال\r\nالوضوء ...................................................................  ١٥٥</p>\n<p class=\"rfdToc2\">الفصل (٢٩) شرائط\r\nالوضوء ..................................................................  ١٦٩</p>\n<p class=\"rfdToc2\">الفصل (٣٠) احكام\r\nالجبائر ...................................................................  ١٩٤</p>\n<p class=\"rfdToc2\">الفصل (٣١) دائم الحدث\r\n.....................................................................  ٢٠٤</p>\n<p class=\"rfdToc2\">الفصل (٣٢) الأغسال ........................................................................  ٢٠٧</p>\n<p class=\"rfdToc2\">الفصل (٣٣) غسل\r\nالجنابة .....................................................................  ٢٠٩</p>\n<p class=\"rfdToc2\">الفصل (٣٤) ما يتوقف\r\nعلى غسل الجنابة .....................................................  ٢١٤</p>\n<p class=\"rfdToc2\">الفصل (٣٥) ما يحرم\r\nعلى الجنب .............................................................  ٢١٥</p>\n<p class=\"rfdToc2\">الفصل (٣٦) ما يكره\r\nعلى الجنب .............................................................  ٢١٩</p>\n<p class=\"rfdToc2\">الفصل (٣٧) كيفية\r\nالغسل وأحكامه ..........................................................  ٢٢٠</p>\n<p class=\"rfdToc2\">الفصل (٣٨) مستحبات\r\nغسل الجنابة .........................................................  ٢٢٨</p>\n<p class=\"rfdToc2\">الفصل (٣٩) الحيض ..........................................................................  ٢٣٥</p>\n<p class=\"rfdToc2\">الفصل (٤٠) تجاوز الدم\r\nعن العشرة ...........................................................  ٢٤٥</p>\n<p class=\"rfdToc2\">الفصل (٤١) أحكام\r\nالحائض ..................................................................  ٢٥٠</p>\n<p class=\"rfdToc2\">الفصل (٤٢) الاستحاضة ......................................................................  ٢٦٠</p>\n<p class=\"rfdToc2\">الفصل (٤٣) النفاس ..........................................................................  ٢٦٩</p>\n<p class=\"rfdToc2\">الفصل (٤٤) غسل مسّ\r\nالميت .................................................................  ٢٧٤</p>\n<p class=\"rfdToc2\">الفصل (٤٥) أحكام\r\nالأموات .................................................................  ٢٧٨</p>\n<p class=\"rfdToc2\">الفصل (٤٦) آداب\r\nالمريض ....................................................................  ٢٨٠</p>\n<p class=\"rfdToc2\">الفصل (٤٧) عيادة\r\nالمريض ....................................................................  ٢٨١</p>\n<p class=\"rfdToc2\">الفصل (٤٨) ما يتعلّق\r\nبالمحتضر ................................................................  ٢٨٢</p>\n<p class=\"rfdToc2\">الفصل (٤٩) المستحبات\r\nبعد الموت ...........................................................  ٢٨٤</p>\n<p class=\"rfdToc2\">الفصل (٥٠) المكروهات\r\nبعد الموت ...........................................................  ٢٨٤</p>\n<p class=\"rfdToc2\">الفصل (٥١) كراهة\r\nالموت ....................................................................  ٢٨٥</p>\n<p class=\"rfdToc2\">الفصل (٥٢) تجهيز\r\nالميت .....................................................................  ٢٨٥</p>\n<p class=\"rfdToc2\">الفصل (٥٣) مراتب\r\nالأولياء ..................................................................  ٢٨٧</p>\n"
}